Shyna_speaks/Shyna_speaks.py
Shyna_speaks/__init__.py
Shyna_speaks/speak_automation.py
Shyna_speaks-0.0.7.dist-info/LICENSE
Shyna_speaks-0.0.7.dist-info/METADATA
Shyna_speaks-0.0.7.dist-info/WHEEL
Shyna_speaks-0.0.7.dist-info/top_level.txt
Shyna_speaks-0.0.7.dist-info/RECORD
