Metadata-Version: 2.1
Name: Shyna-speaks
Version: 0.0.7
Summary: Shyna Speak package, Phase one
Author: Shivam Sharma
Author-email: shivamsharma1913@gmail.com
License-File: LICENSE
Requires-Dist: ShynaDatabase
Requires-Dist: nltk
Requires-Dist: sox
Requires-Dist: setuptools
Requires-Dist: wheel
Requires-Dist: google-speech
